AUTHORS
ChangeLog
README.md
setup.cfg
setup.py
oneview-monasca/.gitignore
oneview-monasca/.pypirc
oneview-monasca/LICENSE.txt
oneview-monasca/README.md
oneview-monasca/oneview_monasca.sh
oneview-monasca/requirements.txt
oneview-monasca/setup.cfg
oneview-monasca/setup.py
oneview-monasca/test-requirements.txt
oneview-monasca/tox.ini
oneview-monasca/docs/Makefile
oneview-monasca/docs/conf.py
oneview-monasca/docs/index.rst
oneview-monasca/docs/make.bat
oneview-monasca/oneview_monasca/__init__.py
oneview-monasca/oneview_monasca/shell.py
oneview-monasca/oneview_monasca/application/__init__.py
oneview-monasca/oneview_monasca/application/coordinator.py
oneview-monasca/oneview_monasca/application/daemon.py
oneview-monasca/oneview_monasca/eventbus/__init__.py
oneview-monasca/oneview_monasca/eventbus/base.py
oneview-monasca/oneview_monasca/eventbus/node_discovery.py
oneview-monasca/oneview_monasca/eventbus/priority.py
oneview-monasca/oneview_monasca/infrastructure/__init__.py
oneview-monasca/oneview_monasca/infrastructure/commands.py
oneview-monasca/oneview_monasca/infrastructure/validations.py
oneview-monasca/oneview_monasca/manager/__init__.py
oneview-monasca/oneview_monasca/manager/abstract_manager_monasca.py
oneview-monasca/oneview_monasca/manager/abstract_manager_oneview.py
oneview-monasca/oneview_monasca/manager/manager_monasca.py
oneview-monasca/oneview_monasca/manager/manager_oneview.py
oneview-monasca/oneview_monasca/model/__init__.py
oneview-monasca/oneview_monasca/model/measurement.py
oneview-monasca/oneview_monasca/model/status.py
oneview-monasca/oneview_monasca/publisher/__init__.py
oneview-monasca/oneview_monasca/publisher/base.py
oneview-monasca/oneview_monasca/publisher/keeper.py
oneview-monasca/oneview_monasca/publisher/puller.py
oneview-monasca/oneview_monasca/publisher/scmb.py
oneview-monasca/oneview_monasca/shared/__init__.py
oneview-monasca/oneview_monasca/shared/constants.py
oneview-monasca/oneview_monasca/shared/exceptions.py
ovm_ironic.egg-info/PKG-INFO
ovm_ironic.egg-info/SOURCES.txt
ovm_ironic.egg-info/dependency_links.txt
ovm_ironic.egg-info/entry_points.txt
ovm_ironic.egg-info/not-zip-safe
ovm_ironic.egg-info/pbr.json
ovm_ironic.egg-info/requires.txt
ovm_ironic.egg-info/top_level.txt
